MANIFEST.in
Makefile
README.rst
__init__.py
dev_req.txt
setup.cfg
setup.py
gottwall_backend_redis.egg-info/PKG-INFO
gottwall_backend_redis.egg-info/SOURCES.txt
gottwall_backend_redis.egg-info/dependency_links.txt
gottwall_backend_redis.egg-info/requires.txt
gottwall_backend_redis.egg-info/top_level.txt
gw_backend_redis/__init__.py
gw_backend_redis/backend.py
gw_backend_redis/processing.py